README.md
setup.py
friendlyscore/__init__.py
friendlyscore/base.py
friendlyscore/cloud.py
friendlyscore/whitelabel.py
friendlyscore.egg-info/PKG-INFO
friendlyscore.egg-info/SOURCES.txt
friendlyscore.egg-info/dependency_links.txt
friendlyscore.egg-info/not-zip-safe
friendlyscore.egg-info/requires.txt
friendlyscore.egg-info/top_level.txt