Metadata-Version: 1.0
Name: friendlyscore
Version: 0.3
Summary: FriendlyScore API client for Cloud and WhiteLabel solution
Home-page: https://github.com/FriendlyScore/FriendlyScore-Python-SDK
Author: Rafał Toboła
Author-email: r.tobola@friendlyscore.com
License: MIT
Platform: UNKNOWN
